air_command/__init__.py
air_command/main.py
air_gesture_command-0.1.3.dist-info/METADATA
air_gesture_command-0.1.3.dist-info/WHEEL
air_gesture_command-0.1.3.dist-info/entry_points.txt
air_gesture_command-0.1.3.dist-info/top_level.txt
air_gesture_command-0.1.3.dist-info/RECORD
