Metadata-Version: 2.4
Name: air-gesture-command
Version: 0.1.3
Summary: Control media players like Youtube, VLC, and Spotify using hand gestures.
Home-page: https://github.com/akshit0942b/air-gesture-command
Author: Akshit
Author-email: Akshit <akshitprajapati24@gmail.com>
License-Expression: MIT
Project-URL: Homepage, https://github.com/akshit0942b/air-gesture-command
Classifier: Programming Language :: Python :: 3
Classifier: Operating System :: MacOS
Classifier: Operating System :: MacOS :: MacOS X
Requires-Python: >=3.7,<3.13
Requires-Dist: opencv-python
Requires-Dist: mediapipe
Requires-Dist: pyautogui
Dynamic: author
Dynamic: home-page
Dynamic: requires-python
